{
	"name": "Layout 1",
	"layers": [
		{
			"name": "Layer 0",
			"overriden": 0,
			"subLayers": [],
			"instances": [
				{
					"type": "TiledBackground",
					"properties": {
						"initially-visible": true,
						"origin": "top-left",
						"wrap-horizontal": "repeat",
						"wrap-vertical": "repeat",
						"image-offset-x": 0,
						"image-offset-y": 0,
						"image-scale-x": 1,
						"image-scale-y": 1,
						"image-angle": 0
					},
					"uid": 2,
					"instanceVariables": {},
					"behaviors": {},
					"world": {
						"x": 0,
						"y": 0,
						"width": 1280,
						"height": 720,
						"originX": 0,
						"originY": 0,
						"color": [
							1,
							1,
							1,
							1
						],
						"angle": 0,
						"zElevation": 0
					}
				},
				{
					"type": "TiledBackground",
					"properties": {
						"initially-visible": true,
						"origin": "top-left",
						"wrap-horizontal": "repeat",
						"wrap-vertical": "repeat",
						"image-offset-x": 0,
						"image-offset-y": 0,
						"image-scale-x": 1,
						"image-scale-y": 1,
						"image-angle": 0
					},
					"uid": 3,
					"instanceVariables": {},
					"behaviors": {},
					"world": {
						"x": 1279.6063018730042,
						"y": -0.19684906349789344,
						"width": 1280,
						"height": 720,
						"originX": 0,
						"originY": 0,
						"color": [
							1,
							1,
							1,
							1
						],
						"angle": 0,
						"zElevation": 0
					}
				},
				{
					"type": "TiledBackground",
					"properties": {
						"initially-visible": true,
						"origin": "top-left",
						"wrap-horizontal": "repeat",
						"wrap-vertical": "repeat",
						"image-offset-x": 0,
						"image-offset-y": 0,
						"image-scale-x": 1,
						"image-scale-y": 1,
						"image-angle": 0
					},
					"uid": 4,
					"instanceVariables": {},
					"behaviors": {},
					"world": {
						"x": 2559.124376750222,
						"y": -0.09282569736751611,
						"width": 1280,
						"height": 720,
						"originX": 0,
						"originY": 0,
						"color": [
							1,
							1,
							1,
							1
						],
						"angle": 0,
						"zElevation": 0
					}
				},
				{
					"type": "TiledBackground",
					"properties": {
						"initially-visible": true,
						"origin": "top-left",
						"wrap-horizontal": "repeat",
						"wrap-vertical": "repeat",
						"image-offset-x": 0,
						"image-offset-y": 0,
						"image-scale-x": 1,
						"image-scale-y": 1,
						"image-angle": 0
					},
					"uid": 5,
					"instanceVariables": {},
					"behaviors": {},
					"world": {
						"x": 3839,
						"y": 0,
						"width": 1280,
						"height": 720,
						"originX": 0,
						"originY": 0,
						"color": [
							1,
							1,
							1,
							1
						],
						"angle": 0,
						"zElevation": 0
					}
				},
				{
					"type": "TiledBackground",
					"properties": {
						"initially-visible": true,
						"origin": "top-left",
						"wrap-horizontal": "repeat",
						"wrap-vertical": "repeat",
						"image-offset-x": 0,
						"image-offset-y": 0,
						"image-scale-x": 1,
						"image-scale-y": 1,
						"image-angle": 0
					},
					"uid": 6,
					"instanceVariables": {},
					"behaviors": {},
					"world": {
						"x": 5119,
						"y": 0,
						"width": 1881,
						"height": 720,
						"originX": 0,
						"originY": 0,
						"color": [
							1,
							1,
							1,
							1
						],
						"angle": 0,
						"zElevation": 0
					}
				},
				{
					"type": "8Tiles",
					"properties": {
						"initially-visible": true,
						"origin": "top-left",
						"wrap-horizontal": "repeat",
						"wrap-vertical": "repeat",
						"image-offset-x": 0,
						"image-offset-y": 0,
						"image-scale-x": 1,
						"image-scale-y": 1,
						"image-angle": 0
					},
					"uid": 7,
					"instanceVariables": {},
					"behaviors": {
						"Solid": {
							"properties": {
								"enabled": true,
								"tags": ""
							}
						}
					},
					"world": {
						"x": 0,
						"y": 624,
						"width": 881,
						"height": 100,
						"originX": 0,
						"originY": 0,
						"color": [
							1,
							1,
							1,
							1
						],
						"angle": 0,
						"zElevation": 0
					}
				},
				{
					"type": "Sprite",
					"properties": {
						"initially-visible": true,
						"initial-animation": "Animation 1",
						"initial-frame": 0,
						"enable-collisions": true,
						"live-preview": false
					},
					"uid": 8,
					"instanceVariables": {},
					"behaviors": {
						"Platform": {
							"properties": {
								"max-speed": 330,
								"acceleration": 1500,
								"deceleration": 1500,
								"jump-strength": 650,
								"gravity": 1500,
								"max-fall-speed": 1000,
								"double-jump": false,
								"jump-sustain": 0,
								"default-controls": true,
								"enabled": true
							}
						},
						"ScrollTo": {
							"properties": {
								"enabled": true
							}
						}
					},
					"world": {
						"x": 98,
						"y": 575,
						"width": 100,
						"height": 99,
						"originX": 0.5,
						"originY": 0.5,
						"color": [
							1,
							1,
							1,
							1
						],
						"angle": 0,
						"zElevation": 0
					}
				},
				{
					"type": "Sprite2",
					"properties": {
						"initially-visible": true,
						"initial-animation": "Animation 1",
						"initial-frame": 0,
						"enable-collisions": true,
						"live-preview": false
					},
					"uid": 9,
					"instanceVariables": {},
					"behaviors": {},
					"world": {
						"x": 493,
						"y": 555,
						"width": 120,
						"height": 120,
						"originX": 0.5,
						"originY": 0.5,
						"color": [
							1,
							1,
							1,
							1
						],
						"angle": 0,
						"zElevation": 0
					}
				},
				{
					"type": "Sprite2",
					"properties": {
						"initially-visible": true,
						"initial-animation": "Animation 1",
						"initial-frame": 0,
						"enable-collisions": true,
						"live-preview": false
					},
					"uid": 10,
					"instanceVariables": {},
					"behaviors": {},
					"world": {
						"x": 493,
						"y": 429,
						"width": 120,
						"height": 120,
						"originX": 0.5,
						"originY": 0.5,
						"color": [
							1,
							1,
							1,
							1
						],
						"angle": 0,
						"zElevation": 0
					}
				},
				{
					"type": "Sprite2",
					"properties": {
						"initially-visible": true,
						"initial-animation": "Animation 1",
						"initial-frame": 0,
						"enable-collisions": true,
						"live-preview": false
					},
					"uid": 11,
					"instanceVariables": {},
					"behaviors": {},
					"world": {
						"x": 494,
						"y": 302,
						"width": 120,
						"height": 120,
						"originX": 0.5,
						"originY": 0.5,
						"color": [
							1,
							1,
							1,
							1
						],
						"angle": 0,
						"zElevation": 0
					}
				},
				{
					"type": "4Tiles",
					"properties": {
						"initially-visible": true,
						"origin": "top-left",
						"wrap-horizontal": "repeat",
						"wrap-vertical": "repeat",
						"image-offset-x": 0,
						"image-offset-y": 0,
						"image-scale-x": 1,
						"image-scale-y": 1,
						"image-angle": 0
					},
					"uid": 12,
					"instanceVariables": {},
					"behaviors": {
						"Solid": {
							"properties": {
								"enabled": true,
								"tags": ""
							}
						}
					},
					"world": {
						"x": 801,
						"y": 398,
						"width": 438,
						"height": 100,
						"originX": 0,
						"originY": 0,
						"color": [
							1,
							1,
							1,
							1
						],
						"angle": 0,
						"zElevation": 0
					}
				},
				{
					"type": "4Tiles",
					"properties": {
						"initially-visible": true,
						"origin": "top-left",
						"wrap-horizontal": "repeat",
						"wrap-vertical": "repeat",
						"image-offset-x": 0,
						"image-offset-y": 0,
						"image-scale-x": 1,
						"image-scale-y": 1,
						"image-angle": 0
					},
					"uid": 13,
					"instanceVariables": {},
					"behaviors": {
						"Solid": {
							"properties": {
								"enabled": true,
								"tags": ""
							}
						}
					},
					"world": {
						"x": 1185,
						"y": 227,
						"width": 438,
						"height": 100,
						"originX": 0,
						"originY": 0,
						"color": [
							1,
							1,
							1,
							1
						],
						"angle": 0,
						"zElevation": 0
					}
				},
				{
					"type": "6Tiles",
					"properties": {
						"initially-visible": true,
						"origin": "top-left",
						"wrap-horizontal": "repeat",
						"wrap-vertical": "repeat",
						"image-offset-x": 0,
						"image-offset-y": 0,
						"image-scale-x": 1,
						"image-scale-y": 1,
						"image-angle": 0
					},
					"uid": 14,
					"instanceVariables": {},
					"behaviors": {
						"Solid": {
							"properties": {
								"enabled": true,
								"tags": ""
							}
						}
					},
					"world": {
						"x": 1527,
						"y": 398,
						"width": 663,
						"height": 100,
						"originX": 0,
						"originY": 0,
						"color": [
							1,
							1,
							1,
							1
						],
						"angle": 0,
						"zElevation": 0
					}
				},
				{
					"type": "Sprite3",
					"properties": {
						"initially-visible": true,
						"initial-animation": "Animation 1",
						"initial-frame": 0,
						"enable-collisions": true,
						"live-preview": false
					},
					"uid": 15,
					"instanceVariables": {},
					"behaviors": {},
					"world": {
						"x": 1403,
						"y": 167,
						"width": 119,
						"height": 114,
						"originX": 0.5,
						"originY": 0.5,
						"color": [
							1,
							1,
							1,
							1
						],
						"angle": 0,
						"zElevation": 0
					}
				},
				{
					"type": "8Tiles",
					"properties": {
						"initially-visible": true,
						"origin": "top-left",
						"wrap-horizontal": "repeat",
						"wrap-vertical": "repeat",
						"image-offset-x": 0,
						"image-offset-y": 0,
						"image-scale-x": 1,
						"image-scale-y": 1,
						"image-angle": 0
					},
					"uid": 16,
					"instanceVariables": {},
					"behaviors": {
						"Solid": {
							"properties": {
								"enabled": true,
								"tags": ""
							}
						}
					},
					"world": {
						"x": 1969,
						"y": 624,
						"width": 881,
						"height": 100,
						"originX": 0,
						"originY": 0,
						"color": [
							1,
							1,
							1,
							1
						],
						"angle": 0,
						"zElevation": 0
					}
				},
				{
					"type": "Sprite4",
					"properties": {
						"initially-visible": true,
						"initial-animation": "Animation 1",
						"initial-frame": 0,
						"enable-collisions": true,
						"live-preview": false
					},
					"uid": 17,
					"instanceVariables": {},
					"behaviors": {},
					"world": {
						"x": 2565.8248586749114,
						"y": 563,
						"width": 124,
						"height": 124,
						"originX": 0.5,
						"originY": 0.5,
						"color": [
							1,
							1,
							1,
							1
						],
						"angle": 0,
						"zElevation": 0
					}
				},
				{
					"type": "Sprite4",
					"properties": {
						"initially-visible": true,
						"initial-animation": "Animation 1",
						"initial-frame": 0,
						"enable-collisions": true,
						"live-preview": false
					},
					"uid": 18,
					"instanceVariables": {},
					"behaviors": {},
					"world": {
						"x": 2443.428839135924,
						"y": 562.4535975732745,
						"width": 124,
						"height": 124,
						"originX": 0.5,
						"originY": 0.5,
						"color": [
							1,
							1,
							1,
							1
						],
						"angle": 0,
						"zElevation": 0
					}
				},
				{
					"type": "3Tiles",
					"properties": {
						"initially-visible": true,
						"origin": "top-left",
						"wrap-horizontal": "repeat",
						"wrap-vertical": "repeat",
						"image-offset-x": 0,
						"image-offset-y": 0,
						"image-scale-x": 1,
						"image-scale-y": 1,
						"image-angle": 0
					},
					"uid": 19,
					"instanceVariables": {},
					"behaviors": {
						"Solid": {
							"properties": {
								"enabled": true,
								"tags": ""
							}
						}
					},
					"world": {
						"x": 2733,
						"y": 398,
						"width": 331,
						"height": 100,
						"originX": 0,
						"originY": 0,
						"color": [
							1,
							1,
							1,
							1
						],
						"angle": 0,
						"zElevation": 0
					}
				},
				{
					"type": "1Tiles",
					"properties": {
						"initially-visible": true,
						"origin": "top-left",
						"wrap-horizontal": "repeat",
						"wrap-vertical": "repeat",
						"image-offset-x": 0,
						"image-offset-y": 0,
						"image-scale-x": 1,
						"image-scale-y": 1,
						"image-angle": 0
					},
					"uid": 20,
					"instanceVariables": {},
					"behaviors": {
						"Solid": {
							"properties": {
								"enabled": true,
								"tags": ""
							}
						}
					},
					"world": {
						"x": 2845,
						"y": 227,
						"width": 112,
						"height": 100,
						"originX": 0,
						"originY": 0,
						"color": [
							1,
							1,
							1,
							1
						],
						"angle": 0,
						"zElevation": 0
					}
				},
				{
					"type": "Sprite5",
					"properties": {
						"initially-visible": true,
						"initial-animation": "Animation 1",
						"initial-frame": 0,
						"enable-collisions": true,
						"live-preview": false
					},
					"uid": 21,
					"instanceVariables": {},
					"behaviors": {},
					"world": {
						"x": 2900,
						"y": 160,
						"width": 128,
						"height": 128,
						"originX": 0.5,
						"originY": 0.5,
						"color": [
							1,
							1,
							1,
							1
						],
						"angle": 0,
						"zElevation": 0
					}
				},
				{
					"type": "8Tiles",
					"properties": {
						"initially-visible": true,
						"origin": "top-left",
						"wrap-horizontal": "repeat",
						"wrap-vertical": "repeat",
						"image-offset-x": 0,
						"image-offset-y": 0,
						"image-scale-x": 1,
						"image-scale-y": 1,
						"image-angle": 0
					},
					"uid": 22,
					"instanceVariables": {},
					"behaviors": {
						"Solid": {
							"properties": {
								"enabled": true,
								"tags": ""
							}
						}
					},
					"world": {
						"x": 2956,
						"y": 624,
						"width": 881,
						"height": 100,
						"originX": 0,
						"originY": 0,
						"color": [
							1,
							1,
							1,
							1
						],
						"angle": 0,
						"zElevation": 0
					}
				},
				{
					"type": "3Tiles",
					"properties": {
						"initially-visible": true,
						"origin": "top-left",
						"wrap-horizontal": "repeat",
						"wrap-vertical": "repeat",
						"image-offset-x": 0,
						"image-offset-y": 0,
						"image-scale-x": 1,
						"image-scale-y": 1,
						"image-angle": 0
					},
					"uid": 23,
					"instanceVariables": {},
					"behaviors": {
						"Solid": {
							"properties": {
								"enabled": true,
								"tags": ""
							}
						}
					},
					"world": {
						"x": 3720,
						"y": 398,
						"width": 880,
						"height": 100,
						"originX": 0,
						"originY": 0,
						"color": [
							1,
							1,
							1,
							1
						],
						"angle": 0,
						"zElevation": 0
					}
				},
				{
					"type": "1Tiles",
					"properties": {
						"initially-visible": true,
						"origin": "top-left",
						"wrap-horizontal": "repeat",
						"wrap-vertical": "repeat",
						"image-offset-x": 0,
						"image-offset-y": 0,
						"image-scale-x": 1,
						"image-scale-y": 1,
						"image-angle": 0
					},
					"uid": 24,
					"instanceVariables": {},
					"behaviors": {
						"Solid": {
							"properties": {
								"enabled": true,
								"tags": ""
							}
						}
					},
					"world": {
						"x": 4348,
						"y": 227,
						"width": 444,
						"height": 100,
						"originX": 0,
						"originY": 0,
						"color": [
							1,
							1,
							1,
							1
						],
						"angle": 0,
						"zElevation": 0
					}
				},
				{
					"type": "Sprite2",
					"properties": {
						"initially-visible": true,
						"initial-animation": "Animation 1",
						"initial-frame": 0,
						"enable-collisions": true,
						"live-preview": false
					},
					"uid": 25,
					"instanceVariables": {},
					"behaviors": {},
					"world": {
						"x": 4659,
						"y": 164,
						"width": 120,
						"height": 120,
						"originX": 0.5,
						"originY": 0.5,
						"color": [
							1,
							1,
							1,
							1
						],
						"angle": 0,
						"zElevation": 0
					}
				},
				{
					"type": "8Tiles",
					"properties": {
						"initially-visible": true,
						"origin": "top-left",
						"wrap-horizontal": "repeat",
						"wrap-vertical": "repeat",
						"image-offset-x": 0,
						"image-offset-y": 0,
						"image-scale-x": 1,
						"image-scale-y": 1,
						"image-angle": 0
					},
					"uid": 26,
					"instanceVariables": {},
					"behaviors": {
						"Solid": {
							"properties": {
								"enabled": true,
								"tags": ""
							}
						}
					},
					"world": {
						"x": 3980,
						"y": 624,
						"width": 881,
						"height": 100,
						"originX": 0,
						"originY": 0,
						"color": [
							1,
							1,
							1,
							1
						],
						"angle": 0,
						"zElevation": 0
					}
				},
				{
					"type": "1Tiles",
					"properties": {
						"initially-visible": true,
						"origin": "top-left",
						"wrap-horizontal": "repeat",
						"wrap-vertical": "repeat",
						"image-offset-x": 0,
						"image-offset-y": 0,
						"image-scale-x": 1,
						"image-scale-y": 1,
						"image-angle": 0
					},
					"uid": 27,
					"instanceVariables": {},
					"behaviors": {
						"Solid": {
							"properties": {
								"enabled": true,
								"tags": ""
							}
						}
					},
					"world": {
						"x": 4950,
						"y": 404,
						"width": 444,
						"height": 100,
						"originX": 0,
						"originY": 0,
						"color": [
							1,
							1,
							1,
							1
						],
						"angle": 0,
						"zElevation": 0
					}
				},
				{
					"type": "8Tiles",
					"properties": {
						"initially-visible": true,
						"origin": "top-left",
						"wrap-horizontal": "repeat",
						"wrap-vertical": "repeat",
						"image-offset-x": 0,
						"image-offset-y": 0,
						"image-scale-x": 1,
						"image-scale-y": 1,
						"image-angle": 0
					},
					"uid": 28,
					"instanceVariables": {},
					"behaviors": {
						"Solid": {
							"properties": {
								"enabled": true,
								"tags": ""
							}
						}
					},
					"world": {
						"x": 4995,
						"y": 624,
						"width": 2003,
						"height": 100,
						"originX": 0,
						"originY": 0,
						"color": [
							1,
							1,
							1,
							1
						],
						"angle": 0,
						"zElevation": 0
					}
				},
				{
					"type": "Sprite5",
					"properties": {
						"initially-visible": true,
						"initial-animation": "Animation 1",
						"initial-frame": 0,
						"enable-collisions": true,
						"live-preview": false
					},
					"uid": 29,
					"instanceVariables": {},
					"behaviors": {},
					"world": {
						"x": 5802,
						"y": 556,
						"width": 128,
						"height": 128,
						"originX": 0.5,
						"originY": 0.5,
						"color": [
							1,
							1,
							1,
							1
						],
						"angle": 0,
						"zElevation": 0
					}
				},
				{
					"type": "Sprite5",
					"properties": {
						"initially-visible": true,
						"initial-animation": "Animation 1",
						"initial-frame": 0,
						"enable-collisions": true,
						"live-preview": false
					},
					"uid": 30,
					"instanceVariables": {},
					"behaviors": {},
					"world": {
						"x": 5802,
						"y": 428,
						"width": 128,
						"height": 128,
						"originX": 0.5,
						"originY": 0.5,
						"color": [
							1,
							1,
							1,
							1
						],
						"angle": 0,
						"zElevation": 0
					}
				},
				{
					"type": "Sprite5",
					"properties": {
						"initially-visible": true,
						"initial-animation": "Animation 1",
						"initial-frame": 0,
						"enable-collisions": true,
						"live-preview": false
					},
					"uid": 31,
					"instanceVariables": {},
					"behaviors": {},
					"world": {
						"x": 5804,
						"y": 300,
						"width": 128,
						"height": 128,
						"originX": 0.5,
						"originY": 0.5,
						"color": [
							1,
							1,
							1,
							1
						],
						"angle": 0,
						"zElevation": 0
					}
				},
				{
					"type": "TiledBackground2",
					"properties": {
						"initially-visible": true,
						"origin": "top-left",
						"wrap-horizontal": "repeat",
						"wrap-vertical": "repeat",
						"image-offset-x": 0,
						"image-offset-y": 0,
						"image-scale-x": 1,
						"image-scale-y": 1,
						"image-angle": 0
					},
					"uid": 32,
					"instanceVariables": {},
					"behaviors": {},
					"world": {
						"x": 6093,
						"y": 283,
						"width": 440,
						"height": 333,
						"originX": 0,
						"originY": 0,
						"color": [
							1,
							1,
							1,
							1
						],
						"angle": 0,
						"zElevation": 0
					}
				},
				{
					"type": "Sprite3",
					"properties": {
						"initially-visible": true,
						"initial-animation": "Animation 1",
						"initial-frame": 0,
						"enable-collisions": true,
						"live-preview": false
					},
					"uid": 33,
					"instanceVariables": {},
					"behaviors": {},
					"world": {
						"x": 6477,
						"y": 224,
						"width": 119,
						"height": 114,
						"originX": 0.5,
						"originY": 0.5,
						"color": [
							1,
							1,
							1,
							1
						],
						"angle": 0,
						"zElevation": 0
					}
				},
				{
					"type": "Sprite6",
					"properties": {
						"initially-visible": true,
						"initial-animation": "Animation 1",
						"initial-frame": 0,
						"enable-collisions": true,
						"live-preview": false
					},
					"uid": 34,
					"instanceVariables": {},
					"behaviors": {},
					"world": {
						"x": 6909,
						"y": 468,
						"width": 170,
						"height": 306,
						"originX": 0.5,
						"originY": 0.5,
						"color": [
							1,
							1,
							1,
							1
						],
						"angle": 0,
						"zElevation": 0
					}
				},
				{
					"type": "Sprite7",
					"properties": {
						"initially-visible": true,
						"initial-animation": "Animation 1",
						"initial-frame": 0,
						"enable-collisions": true,
						"live-preview": false
					},
					"uid": 36,
					"instanceVariables": {},
					"behaviors": {},
					"world": {
						"x": 236,
						"y": 35,
						"width": 198,
						"height": 100,
						"originX": 0.5,
						"originY": 0.5,
						"color": [
							1,
							1,
							1,
							1
						],
						"angle": 0,
						"zElevation": 0
					}
				}
			],
			"sid": 861932136905514,
			"effectTypes": [],
			"isInitiallyVisible": true,
			"isInitiallyInteractive": true,
			"color": [
				1,
				1,
				1,
				1
			],
			"backgroundColor": [
				0.3686274509803922,
				0.3686274509803922,
				0.3686274509803922,
				1
			],
			"isTransparent": false,
			"parallaxX": 1,
			"parallaxY": 1,
			"scaleRate": 1,
			"forceOwnTexture": false,
			"renderingMode": "3d",
			"drawOrder": "z-order",
			"useRenderCells": false,
			"blendMode": "normal",
			"zElevation": 0,
			"global": false
		}
	],
	"sid": 765709783550696,
	"nonworld-instances": [],
	"effectTypes": [],
	"width": 7000,
	"height": 720,
	"unboundedScrolling": false,
	"vpX": 0.5,
	"vpY": 0.5,
	"projection": "perspective",
	"eventSheet": "Event sheet 1"
}