{
	"name": "es_lv1",
	"events": [
		{
			"eventType": "block",
			"conditions": [
				{
					"id": "on-start-of-layout",
					"objectClass": "System",
					"sid": 206555566233172
				}
			],
			"actions": [
				{
					"id": "set-instvar-value",
					"objectClass": "Mainplayer",
					"sid": 277154153548108,
					"parameters": {
						"instance-variable": "Heart",
						"value": "3"
					}
				},
				{
					"id": "set-jump-strength",
					"objectClass": "Mainplayer",
					"sid": 476561678825257,
					"behaviorType": "Platform",
					"parameters": {
						"jump-strength": "800"
					}
				},
				{
					"id": "set-double-jump",
					"objectClass": "Mainplayer",
					"sid": 883185515939410,
					"behaviorType": "Platform",
					"parameters": {
						"state": "enabled"
					}
				},
				{
					"id": "set-position",
					"objectClass": "Mainplayer",
					"sid": 317235024790397,
					"parameters": {
						"x": "130",
						"y": "400"
					}
				},
				{
					"id": "wait",
					"objectClass": "System",
					"sid": 117831659180640,
					"parameters": {
						"seconds": "1.5"
					}
				},
				{
					"id": "set-enabled",
					"objectClass": "Mainplayer",
					"sid": 899271063878497,
					"behaviorType": "Platform",
					"parameters": {
						"state": "enabled"
					}
				},
				{
					"id": "move-to-top",
					"objectClass": "Mainplayer",
					"sid": 830660061507188
				}
			],
			"sid": 962953025319465,
			"children": [
				{
					"eventType": "block",
					"conditions": [
						{
							"id": "is-tag-playing",
							"objectClass": "Audio",
							"sid": 860739870536803,
							"parameters": {
								"tag": "\"BGsound\""
							},
							"isInverted": true
						}
					],
					"actions": [
						{
							"id": "play",
							"objectClass": "Audio",
							"sid": 663140735008751,
							"parameters": {
								"audio-file": "X2Download.app - Professor Layton and the Last Time Travel OST 28 - The Professor's Trunk (Minicar) (HQ Version) (128 kbps)",
								"loop": "looping",
								"volume": "40",
								"stereo-pan": "0",
								"tag-optional": "\"BGsound\""
							}
						}
					],
					"sid": 649743821001260
				}
			]
		},
		{
			"eventType": "block",
			"conditions": [],
			"actions": [],
			"sid": 970720249662704
		},
		{
			"eventType": "block",
			"conditions": [
				{
					"id": "is-on-screen",
					"objectClass": "Mainplayer",
					"sid": 573976029658103
				}
			],
			"actions": [
				{
					"id": "set-text",
					"objectClass": "lv1_heart",
					"sid": 687179588669133,
					"parameters": {
						"text": "Mainplayer.Heart"
					}
				},
				{
					"id": "set-text",
					"objectClass": "lv1_poin",
					"sid": 416523379703041,
					"parameters": {
						"text": "Mainplayer.poin"
					}
				}
			],
			"sid": 573807132728793
		},
		{
			"eventType": "block",
			"conditions": [
				{
					"id": "compare-instance-variable",
					"objectClass": "Mainplayer",
					"sid": 179764080763885,
					"parameters": {
						"instance-variable": "Heart",
						"comparison": 0,
						"value": "0"
					}
				}
			],
			"actions": [
				{
					"id": "play",
					"objectClass": "Audio",
					"sid": 854553381132925,
					"parameters": {
						"audio-file": "game over",
						"loop": "not-looping",
						"volume": "80",
						"stereo-pan": "0",
						"tag-optional": "\"gameover\""
					}
				},
				{
					"id": "set-enabled",
					"objectClass": "Mainplayer",
					"sid": 339119887944356,
					"behaviorType": "Platform",
					"parameters": {
						"state": "disabled"
					}
				},
				{
					"id": "wait",
					"objectClass": "System",
					"sid": 214158662460129,
					"parameters": {
						"seconds": "1.0"
					}
				},
				{
					"id": "set-position",
					"objectClass": "onGameOver",
					"sid": 137896811270993,
					"parameters": {
						"x": "pauseimg.X-700",
						"y": "LayoutHeight/2"
					}
				},
				{
					"id": "wait",
					"objectClass": "System",
					"sid": 687649395643443,
					"parameters": {
						"seconds": "1.7"
					}
				},
				{
					"id": "stop",
					"objectClass": "Audio",
					"sid": 686188899847485,
					"parameters": {
						"tag": "\"gameover\""
					}
				}
			],
			"sid": 642807874058080
		},
		{
			"eventType": "block",
			"conditions": [
				{
					"id": "on-object-clicked",
					"objectClass": "Mouse",
					"sid": 923826832773458,
					"parameters": {
						"mouse-button": "left",
						"click-type": "clicked",
						"object-clicked": "lv1_GameOverReset"
					}
				}
			],
			"actions": [
				{
					"id": "go-to-layout",
					"objectClass": "System",
					"sid": 849164053722649,
					"parameters": {
						"layout": "LV1"
					}
				}
			],
			"sid": 566670825001181
		},
		{
			"eventType": "block",
			"conditions": [
				{
					"id": "on-tap-object",
					"objectClass": "Touch",
					"sid": 577129466026460,
					"parameters": {
						"object": "lv1_GameOverReset"
					}
				}
			],
			"actions": [
				{
					"id": "go-to-layout",
					"objectClass": "System",
					"sid": 167492326850673,
					"parameters": {
						"layout": "LV1"
					}
				}
			],
			"sid": 735077089821646
		},
		{
			"eventType": "block",
			"conditions": [
				{
					"id": "on-object-clicked",
					"objectClass": "Mouse",
					"sid": 385791357867597,
					"parameters": {
						"mouse-button": "left",
						"click-type": "clicked",
						"object-clicked": "lv1_GameOverMenu"
					}
				}
			],
			"actions": [
				{
					"id": "go-to-layout",
					"objectClass": "System",
					"sid": 719548341349142,
					"parameters": {
						"layout": "PilihLv"
					}
				},
				{
					"id": "move-to-bottom",
					"objectClass": "Mainplayer",
					"sid": 812103085300586
				},
				{
					"id": "stop-all",
					"objectClass": "Audio",
					"sid": 974733920167365
				}
			],
			"sid": 120729264284735
		},
		{
			"eventType": "block",
			"conditions": [
				{
					"id": "on-tap-object",
					"objectClass": "Touch",
					"sid": 652696387875967,
					"parameters": {
						"object": "lv1_GameOverMenu"
					}
				}
			],
			"actions": [
				{
					"id": "go-to-layout",
					"objectClass": "System",
					"sid": 921547243684815,
					"parameters": {
						"layout": "PilihLv"
					}
				},
				{
					"id": "move-to-bottom",
					"objectClass": "Mainplayer",
					"sid": 967029172856105
				}
			],
			"sid": 463742620861621
		},
		{
			"eventType": "block",
			"conditions": [
				{
					"id": "on-object-clicked",
					"objectClass": "Mouse",
					"sid": 230464496829389,
					"parameters": {
						"mouse-button": "left",
						"click-type": "clicked",
						"object-clicked": "pauseimg"
					}
				}
			],
			"actions": [
				{
					"id": "tween-one-property",
					"objectClass": "Pausedisp",
					"sid": 873910736916041,
					"behaviorType": "Tween",
					"parameters": {
						"tags": "\"\"",
						"property": "offsetX",
						"end-value": "pauseimg.X-734",
						"time": "1",
						"ease": "default",
						"destroy-on-complete": "no",
						"loop": "no",
						"ping-pong": "no",
						"repeat-count": "1"
					}
				}
			],
			"sid": 366315060942972
		},
		{
			"eventType": "block",
			"conditions": [
				{
					"id": "on-tap-object",
					"objectClass": "Touch",
					"sid": 237346787001988,
					"parameters": {
						"object": "pauseimg"
					}
				}
			],
			"actions": [
				{
					"id": "tween-one-property",
					"objectClass": "Pausedisp",
					"sid": 563821626532488,
					"behaviorType": "Tween",
					"parameters": {
						"tags": "\"\"",
						"property": "offsetX",
						"end-value": "pauseimg.X-734",
						"time": "1",
						"ease": "default",
						"destroy-on-complete": "no",
						"loop": "no",
						"ping-pong": "no",
						"repeat-count": "1"
					}
				}
			],
			"sid": 112712262676706
		},
		{
			"eventType": "block",
			"conditions": [
				{
					"id": "on-object-clicked",
					"objectClass": "Mouse",
					"sid": 594736629782049,
					"parameters": {
						"mouse-button": "left",
						"click-type": "clicked",
						"object-clicked": "lv1_pause_resume"
					}
				}
			],
			"actions": [
				{
					"id": "tween-one-property",
					"objectClass": "Pausedisp",
					"sid": 458568068214214,
					"behaviorType": "Tween",
					"parameters": {
						"tags": "\"\"",
						"property": "offsetX",
						"end-value": "-734",
						"time": "1",
						"ease": "default",
						"destroy-on-complete": "no",
						"loop": "no",
						"ping-pong": "no",
						"repeat-count": "1"
					}
				},
				{
					"id": "set-enabled",
					"objectClass": "Mainplayer",
					"sid": 161489498380102,
					"behaviorType": "Platform",
					"parameters": {
						"state": "enabled"
					}
				}
			],
			"sid": 155207313242606
		},
		{
			"eventType": "block",
			"conditions": [
				{
					"id": "on-tap-object",
					"objectClass": "Touch",
					"sid": 808151351759886,
					"parameters": {
						"object": "lv1_pause_resume"
					}
				}
			],
			"actions": [
				{
					"id": "tween-one-property",
					"objectClass": "Pausedisp",
					"sid": 483665622246279,
					"behaviorType": "Tween",
					"parameters": {
						"tags": "\"\"",
						"property": "offsetX",
						"end-value": "-734",
						"time": "1",
						"ease": "default",
						"destroy-on-complete": "no",
						"loop": "no",
						"ping-pong": "no",
						"repeat-count": "1"
					}
				},
				{
					"id": "set-enabled",
					"objectClass": "Mainplayer",
					"sid": 947078386222168,
					"behaviorType": "Platform",
					"parameters": {
						"state": "enabled"
					}
				}
			],
			"sid": 115263627161849
		},
		{
			"eventType": "block",
			"conditions": [
				{
					"id": "on-object-clicked",
					"objectClass": "Mouse",
					"sid": 526435679313061,
					"parameters": {
						"mouse-button": "left",
						"click-type": "clicked",
						"object-clicked": "lv1_pause_reset"
					}
				}
			],
			"actions": [
				{
					"id": "go-to-layout",
					"objectClass": "System",
					"sid": 478434703656417,
					"parameters": {
						"layout": "LV1"
					}
				}
			],
			"sid": 762123250434525
		},
		{
			"eventType": "block",
			"conditions": [
				{
					"id": "on-tap-object",
					"objectClass": "Touch",
					"sid": 578842663232823,
					"parameters": {
						"object": "lv1_pause_reset"
					}
				}
			],
			"actions": [
				{
					"id": "go-to-layout",
					"objectClass": "System",
					"sid": 200821767800769,
					"parameters": {
						"layout": "LV1"
					}
				}
			],
			"sid": 108772467929397
		},
		{
			"eventType": "block",
			"conditions": [
				{
					"id": "on-object-clicked",
					"objectClass": "Mouse",
					"sid": 745652934081568,
					"parameters": {
						"mouse-button": "left",
						"click-type": "clicked",
						"object-clicked": "lv1_pause_menu"
					}
				}
			],
			"actions": [
				{
					"id": "go-to-layout",
					"objectClass": "System",
					"sid": 830267943059306,
					"parameters": {
						"layout": "PilihLv"
					}
				},
				{
					"id": "move-to-bottom",
					"objectClass": "Mainplayer",
					"sid": 972216579697854
				},
				{
					"id": "stop-all",
					"objectClass": "Audio",
					"sid": 381293632993564
				}
			],
			"sid": 362524324214061
		},
		{
			"eventType": "block",
			"conditions": [
				{
					"id": "on-tap-object",
					"objectClass": "Touch",
					"sid": 816601481295266,
					"parameters": {
						"object": "lv1_pause_menu"
					}
				}
			],
			"actions": [
				{
					"id": "go-to-layout",
					"objectClass": "System",
					"sid": 292329208016629,
					"parameters": {
						"layout": "PilihLv"
					}
				},
				{
					"id": "move-to-bottom",
					"objectClass": "Mainplayer",
					"sid": 487863137919887
				},
				{
					"id": "stop-all",
					"objectClass": "Audio",
					"sid": 359230251209432
				}
			],
			"sid": 461540391316810
		},
		{
			"eventType": "block",
			"conditions": [
				{
					"id": "on-object-clicked",
					"objectClass": "Mouse",
					"sid": 281922826329856,
					"parameters": {
						"mouse-button": "left",
						"click-type": "clicked",
						"object-clicked": "lv1_pause_mute"
					}
				}
			],
			"actions": [
				{
					"id": "set-muted",
					"objectClass": "Audio",
					"sid": 784811932615609,
					"parameters": {
						"tag": "\"BGsound\"",
						"state": "muted"
					}
				}
			],
			"sid": 773288280024582
		},
		{
			"eventType": "block",
			"conditions": [
				{
					"id": "on-tap-object",
					"objectClass": "Touch",
					"sid": 958298967505707,
					"parameters": {
						"object": "lv1_pause_mute"
					}
				}
			],
			"actions": [
				{
					"id": "set-muted",
					"objectClass": "Audio",
					"sid": 246812359867564,
					"parameters": {
						"tag": "\"BGsound\"",
						"state": "muted"
					}
				}
			],
			"sid": 103485191165505
		},
		{
			"eventType": "block",
			"conditions": [
				{
					"id": "on-key-pressed",
					"objectClass": "Keyboard",
					"sid": 547331033869416,
					"parameters": {
						"key": 39
					}
				}
			],
			"actions": [
				{
					"id": "set-mirrored",
					"objectClass": "Mainplayer",
					"sid": 571722487339737,
					"parameters": {
						"state": "not-mirrored"
					}
				}
			],
			"sid": 363183320320643
		},
		{
			"eventType": "block",
			"conditions": [
				{
					"id": "on-key-pressed",
					"objectClass": "Keyboard",
					"sid": 215433796566941,
					"parameters": {
						"key": 37
					}
				}
			],
			"actions": [
				{
					"id": "set-mirrored",
					"objectClass": "Mainplayer",
					"sid": 423821368943288,
					"parameters": {
						"state": "mirrored"
					}
				}
			],
			"sid": 675464416303794
		},
		{
			"eventType": "block",
			"conditions": [
				{
					"id": "cursor-is-over-object",
					"objectClass": "Mouse",
					"sid": 145802997952071,
					"parameters": {
						"object": "CtrlR"
					}
				}
			],
			"actions": [
				{
					"id": "set-mirrored",
					"objectClass": "Mainplayer",
					"sid": 396003589304968,
					"parameters": {
						"state": "not-mirrored"
					}
				},
				{
					"id": "simulate-control",
					"objectClass": "Mainplayer",
					"sid": 388763321543252,
					"behaviorType": "Platform",
					"parameters": {
						"control": "right"
					}
				}
			],
			"sid": 438545838509451
		},
		{
			"eventType": "block",
			"conditions": [
				{
					"id": "cursor-is-over-object",
					"objectClass": "Mouse",
					"sid": 875182771024438,
					"parameters": {
						"object": "CtrlL"
					}
				}
			],
			"actions": [
				{
					"id": "set-mirrored",
					"objectClass": "Mainplayer",
					"sid": 652766921378908,
					"parameters": {
						"state": "mirrored"
					}
				},
				{
					"id": "simulate-control",
					"objectClass": "Mainplayer",
					"sid": 184181734279997,
					"behaviorType": "Platform",
					"parameters": {
						"control": "left"
					}
				}
			],
			"sid": 424785335221898
		},
		{
			"eventType": "block",
			"conditions": [
				{
					"id": "cursor-is-over-object",
					"objectClass": "Mouse",
					"sid": 463249799708980,
					"parameters": {
						"object": "CtrlU"
					}
				},
				{
					"id": "is-jumping",
					"objectClass": "Mainplayer",
					"sid": 255639387904581,
					"behaviorType": "Platform",
					"isInverted": true
				}
			],
			"actions": [
				{
					"id": "simulate-control",
					"objectClass": "Mainplayer",
					"sid": 658364221598176,
					"behaviorType": "Platform",
					"parameters": {
						"control": "jump"
					}
				},
				{
					"id": "play",
					"objectClass": "Audio",
					"sid": 608879184551823,
					"parameters": {
						"audio-file": "lompat",
						"loop": "not-looping",
						"volume": "60",
						"stereo-pan": "0",
						"tag-optional": "\"\""
					}
				}
			],
			"sid": 333933507599543
		},
		{
			"eventType": "block",
			"conditions": [
				{
					"id": "is-touching-object",
					"objectClass": "Touch",
					"sid": 526458542944201,
					"parameters": {
						"object": "CtrlR"
					}
				}
			],
			"actions": [
				{
					"id": "set-mirrored",
					"objectClass": "Mainplayer",
					"sid": 798446575915070,
					"parameters": {
						"state": "not-mirrored"
					}
				},
				{
					"id": "simulate-control",
					"objectClass": "Mainplayer",
					"sid": 828518918303357,
					"behaviorType": "Platform",
					"parameters": {
						"control": "right"
					}
				}
			],
			"sid": 993442637547054
		},
		{
			"eventType": "block",
			"conditions": [
				{
					"id": "is-touching-object",
					"objectClass": "Touch",
					"sid": 475391127941000,
					"parameters": {
						"object": "CtrlL"
					}
				}
			],
			"actions": [
				{
					"id": "set-mirrored",
					"objectClass": "Mainplayer",
					"sid": 100058660027253,
					"parameters": {
						"state": "mirrored"
					}
				},
				{
					"id": "simulate-control",
					"objectClass": "Mainplayer",
					"sid": 982166330042586,
					"behaviorType": "Platform",
					"parameters": {
						"control": "left"
					}
				}
			],
			"sid": 997710260953867
		},
		{
			"eventType": "block",
			"conditions": [
				{
					"id": "on-tap-object",
					"objectClass": "Touch",
					"sid": 399931193575572,
					"parameters": {
						"object": "CtrlU"
					}
				},
				{
					"id": "is-jumping",
					"objectClass": "Mainplayer",
					"sid": 737276263563212,
					"behaviorType": "Platform",
					"isInverted": true
				}
			],
			"actions": [
				{
					"id": "simulate-control",
					"objectClass": "Mainplayer",
					"sid": 965095477946976,
					"behaviorType": "Platform",
					"parameters": {
						"control": "jump"
					}
				},
				{
					"id": "play",
					"objectClass": "Audio",
					"sid": 505451403824011,
					"parameters": {
						"audio-file": "lompat",
						"loop": "not-looping",
						"volume": "60",
						"stereo-pan": "0",
						"tag-optional": "\"\""
					}
				}
			],
			"sid": 306354609176687
		},
		{
			"eventType": "block",
			"conditions": [
				{
					"id": "compare-y",
					"objectClass": "Mainplayer",
					"sid": 433837476679162,
					"parameters": {
						"comparison": 4,
						"y-co-ordinate": "900"
					}
				}
			],
			"actions": [
				{
					"id": "set-position",
					"objectClass": "Mainplayer",
					"sid": 260958975365522,
					"parameters": {
						"x": "150",
						"y": "450"
					}
				},
				{
					"id": "subtract-from-instvar",
					"objectClass": "Mainplayer",
					"sid": 712312585037654,
					"parameters": {
						"instance-variable": "Heart",
						"value": "1"
					}
				}
			],
			"sid": 517608989752688
		},
		{
			"eventType": "block",
			"conditions": [
				{
					"id": "on-collision-with-another-object",
					"objectClass": "finish",
					"sid": 367967628466879,
					"parameters": {
						"object": "Mainplayer"
					}
				}
			],
			"actions": [
				{
					"id": "tween-one-property",
					"objectClass": "finishPopuplv1",
					"sid": 979759278077286,
					"behaviorType": "Tween",
					"parameters": {
						"tags": "\"\"",
						"property": "offsetY",
						"end-value": "LayoutHeight/2",
						"time": "1",
						"ease": "easeinback",
						"destroy-on-complete": "no",
						"loop": "no",
						"ping-pong": "no",
						"repeat-count": "1"
					}
				},
				{
					"id": "set-enabled",
					"objectClass": "Mainplayer",
					"sid": 281998148506200,
					"behaviorType": "Platform",
					"parameters": {
						"state": "disabled"
					}
				},
				{
					"id": "play",
					"objectClass": "Audio",
					"sid": 505965410240603,
					"parameters": {
						"audio-file": "X2Download.app - 🎮👾 Retro Video Game Arcade 8 Bit [Sound Effects] Free Download Audio Background for Edits (128 kbps)-[AudioTrimmer.com]",
						"loop": "not-looping",
						"volume": "50",
						"stereo-pan": "0",
						"tag-optional": "\"\""
					}
				},
				{
					"id": "fade-volume",
					"objectClass": "Audio",
					"sid": 947665728893199,
					"parameters": {
						"tag": "\"BGsound\"",
						"db": "-100",
						"duration": "3",
						"ending": "stop"
					}
				}
			],
			"sid": 937139320633691
		},
		{
			"eventType": "block",
			"conditions": [
				{
					"id": "on-object-clicked",
					"objectClass": "Mouse",
					"sid": 249695816994276,
					"parameters": {
						"mouse-button": "left",
						"click-type": "clicked",
						"object-clicked": "finishClickAny"
					}
				}
			],
			"actions": [
				{
					"id": "tween-one-property",
					"objectClass": "finishPopuplv1",
					"sid": 647264736849164,
					"behaviorType": "Tween",
					"parameters": {
						"tags": "\"\"",
						"property": "offsetY",
						"end-value": "-300",
						"time": "1",
						"ease": "easeoutback",
						"destroy-on-complete": "no",
						"loop": "no",
						"ping-pong": "no",
						"repeat-count": "1"
					}
				},
				{
					"id": "go-to-layout",
					"objectClass": "System",
					"sid": 793643745841689,
					"parameters": {
						"layout": "PilihLv"
					}
				}
			],
			"sid": 561616549538829
		},
		{
			"eventType": "block",
			"conditions": [
				{
					"id": "on-tap-object",
					"objectClass": "Touch",
					"sid": 962651382956453,
					"parameters": {
						"object": "finishClickAny"
					}
				}
			],
			"actions": [
				{
					"id": "tween-one-property",
					"objectClass": "finishPopuplv1",
					"sid": 181878471046194,
					"behaviorType": "Tween",
					"parameters": {
						"tags": "\"\"",
						"property": "offsetY",
						"end-value": "-300",
						"time": "1",
						"ease": "easeoutback",
						"destroy-on-complete": "no",
						"loop": "no",
						"ping-pong": "no",
						"repeat-count": "1"
					}
				},
				{
					"id": "go-to-layout",
					"objectClass": "System",
					"sid": 654942692901392,
					"parameters": {
						"layout": "PilihLv"
					}
				}
			],
			"sid": 116051937114995
		},
		{
			"eventType": "block",
			"conditions": [
				{
					"id": "on-object-clicked",
					"objectClass": "Mouse",
					"sid": 879012700129097,
					"parameters": {
						"mouse-button": "left",
						"click-type": "clicked",
						"object-clicked": "rightans"
					}
				}
			],
			"actions": [
				{
					"id": "tween-one-property",
					"objectClass": "lv1_q1",
					"sid": 746762165762662,
					"behaviorType": "Tween",
					"parameters": {
						"tags": "\"\"",
						"property": "offsetY",
						"end-value": "-500",
						"time": "1",
						"ease": "default",
						"destroy-on-complete": "no",
						"loop": "no",
						"ping-pong": "no",
						"repeat-count": "1"
					}
				},
				{
					"id": "tween-one-property",
					"objectClass": "lv1_q2",
					"sid": 198993722972361,
					"behaviorType": "Tween",
					"parameters": {
						"tags": "\"\"",
						"property": "offsetY",
						"end-value": "-500",
						"time": "1",
						"ease": "default",
						"destroy-on-complete": "no",
						"loop": "no",
						"ping-pong": "no",
						"repeat-count": "1"
					}
				},
				{
					"id": "tween-one-property",
					"objectClass": "lv1_q3",
					"sid": 182865361805388,
					"behaviorType": "Tween",
					"parameters": {
						"tags": "\"\"",
						"property": "offsetY",
						"end-value": "-500",
						"time": "1",
						"ease": "default",
						"destroy-on-complete": "no",
						"loop": "no",
						"ping-pong": "no",
						"repeat-count": "1"
					}
				},
				{
					"id": "tween-one-property",
					"objectClass": "lv1_q4",
					"sid": 895166485386031,
					"behaviorType": "Tween",
					"parameters": {
						"tags": "\"\"",
						"property": "offsetY",
						"end-value": "-500",
						"time": "1",
						"ease": "default",
						"destroy-on-complete": "no",
						"loop": "no",
						"ping-pong": "no",
						"repeat-count": "1"
					}
				},
				{
					"id": "tween-one-property",
					"objectClass": "lv1_q5",
					"sid": 616278025788251,
					"behaviorType": "Tween",
					"parameters": {
						"tags": "\"\"",
						"property": "offsetY",
						"end-value": "-500",
						"time": "1",
						"ease": "default",
						"destroy-on-complete": "no",
						"loop": "no",
						"ping-pong": "no",
						"repeat-count": "1"
					}
				},
				{
					"id": "tween-one-property",
					"objectClass": "lv1_q6",
					"sid": 505590939901490,
					"behaviorType": "Tween",
					"parameters": {
						"tags": "\"\"",
						"property": "offsetY",
						"end-value": "-500",
						"time": "1",
						"ease": "default",
						"destroy-on-complete": "no",
						"loop": "no",
						"ping-pong": "no",
						"repeat-count": "1"
					}
				},
				{
					"id": "subtract-from-instvar",
					"objectClass": "Mainplayer",
					"sid": 361485910203465,
					"parameters": {
						"instance-variable": "poin",
						"value": "-5"
					}
				},
				{
					"id": "set-visible",
					"objectClass": "popupJawabanBenar",
					"sid": 340125905657041,
					"parameters": {
						"visibility": "visible"
					}
				},
				{
					"id": "set-position",
					"objectClass": "popupJawabanBenar",
					"sid": 546902190138401,
					"parameters": {
						"x": "pauseimg.X-735",
						"y": "LayoutHeight/2"
					}
				},
				{
					"id": "wait",
					"objectClass": "System",
					"sid": 523562021331151,
					"parameters": {
						"seconds": "2.0"
					}
				},
				{
					"id": "set-visible",
					"objectClass": "popupJawabanBenar",
					"sid": 836437612595171,
					"parameters": {
						"visibility": "invisible"
					}
				},
				{
					"id": "set-enabled",
					"objectClass": "Mainplayer",
					"sid": 736576302263569,
					"behaviorType": "Platform",
					"parameters": {
						"state": "enabled"
					}
				}
			],
			"sid": 992400356253628
		},
		{
			"eventType": "block",
			"conditions": [
				{
					"id": "on-tap-object",
					"objectClass": "Touch",
					"sid": 478667744713900,
					"parameters": {
						"object": "rightans"
					}
				}
			],
			"actions": [
				{
					"id": "tween-one-property",
					"objectClass": "lv1_q1",
					"sid": 473927009570918,
					"behaviorType": "Tween",
					"parameters": {
						"tags": "\"\"",
						"property": "offsetY",
						"end-value": "-500",
						"time": "1",
						"ease": "default",
						"destroy-on-complete": "no",
						"loop": "no",
						"ping-pong": "no",
						"repeat-count": "1"
					}
				},
				{
					"id": "tween-one-property",
					"objectClass": "lv1_q2",
					"sid": 497882381722430,
					"behaviorType": "Tween",
					"parameters": {
						"tags": "\"\"",
						"property": "offsetY",
						"end-value": "-500",
						"time": "1",
						"ease": "default",
						"destroy-on-complete": "no",
						"loop": "no",
						"ping-pong": "no",
						"repeat-count": "1"
					}
				},
				{
					"id": "tween-one-property",
					"objectClass": "lv1_q3",
					"sid": 961367974889715,
					"behaviorType": "Tween",
					"parameters": {
						"tags": "\"\"",
						"property": "offsetY",
						"end-value": "-500",
						"time": "1",
						"ease": "default",
						"destroy-on-complete": "no",
						"loop": "no",
						"ping-pong": "no",
						"repeat-count": "1"
					}
				},
				{
					"id": "tween-one-property",
					"objectClass": "lv1_q4",
					"sid": 211096797130183,
					"behaviorType": "Tween",
					"parameters": {
						"tags": "\"\"",
						"property": "offsetY",
						"end-value": "-500",
						"time": "1",
						"ease": "default",
						"destroy-on-complete": "no",
						"loop": "no",
						"ping-pong": "no",
						"repeat-count": "1"
					}
				},
				{
					"id": "tween-one-property",
					"objectClass": "lv1_q5",
					"sid": 562635565369688,
					"behaviorType": "Tween",
					"parameters": {
						"tags": "\"\"",
						"property": "offsetY",
						"end-value": "-500",
						"time": "1",
						"ease": "default",
						"destroy-on-complete": "no",
						"loop": "no",
						"ping-pong": "no",
						"repeat-count": "1"
					}
				},
				{
					"id": "tween-one-property",
					"objectClass": "lv1_q6",
					"sid": 864653450644409,
					"behaviorType": "Tween",
					"parameters": {
						"tags": "\"\"",
						"property": "offsetY",
						"end-value": "-500",
						"time": "1",
						"ease": "default",
						"destroy-on-complete": "no",
						"loop": "no",
						"ping-pong": "no",
						"repeat-count": "1"
					}
				},
				{
					"id": "subtract-from-instvar",
					"objectClass": "Mainplayer",
					"sid": 788136337895678,
					"parameters": {
						"instance-variable": "poin",
						"value": "-5"
					}
				},
				{
					"id": "set-visible",
					"objectClass": "popupJawabanBenar",
					"sid": 254364843943707,
					"parameters": {
						"visibility": "visible"
					}
				},
				{
					"id": "set-position",
					"objectClass": "popupJawabanBenar",
					"sid": 754435403469298,
					"parameters": {
						"x": "pauseimg.X-735",
						"y": "LayoutHeight/2"
					}
				},
				{
					"id": "wait",
					"objectClass": "System",
					"sid": 151131405619406,
					"parameters": {
						"seconds": "2.0"
					}
				},
				{
					"id": "set-visible",
					"objectClass": "popupJawabanBenar",
					"sid": 849694995264073,
					"parameters": {
						"visibility": "invisible"
					}
				},
				{
					"id": "set-enabled",
					"objectClass": "Mainplayer",
					"sid": 662506966450475,
					"behaviorType": "Platform",
					"parameters": {
						"state": "enabled"
					}
				}
			],
			"sid": 113276466726503
		},
		{
			"eventType": "block",
			"conditions": [
				{
					"id": "on-object-clicked",
					"objectClass": "Mouse",
					"sid": 195881300060067,
					"parameters": {
						"mouse-button": "left",
						"click-type": "clicked",
						"object-clicked": "wrongans"
					}
				}
			],
			"actions": [
				{
					"id": "tween-one-property",
					"objectClass": "lv1_q1",
					"sid": 304093078995527,
					"behaviorType": "Tween",
					"parameters": {
						"tags": "\"\"",
						"property": "offsetY",
						"end-value": "-500",
						"time": "1",
						"ease": "default",
						"destroy-on-complete": "no",
						"loop": "no",
						"ping-pong": "no",
						"repeat-count": "1"
					}
				},
				{
					"id": "tween-one-property",
					"objectClass": "lv1_q2",
					"sid": 485301017090445,
					"behaviorType": "Tween",
					"parameters": {
						"tags": "\"\"",
						"property": "offsetY",
						"end-value": "-500",
						"time": "1",
						"ease": "default",
						"destroy-on-complete": "no",
						"loop": "no",
						"ping-pong": "no",
						"repeat-count": "1"
					}
				},
				{
					"id": "tween-one-property",
					"objectClass": "lv1_q3",
					"sid": 643891474910200,
					"behaviorType": "Tween",
					"parameters": {
						"tags": "\"\"",
						"property": "offsetY",
						"end-value": "-500",
						"time": "1",
						"ease": "default",
						"destroy-on-complete": "no",
						"loop": "no",
						"ping-pong": "no",
						"repeat-count": "1"
					}
				},
				{
					"id": "tween-one-property",
					"objectClass": "lv1_q4",
					"sid": 734629046392094,
					"behaviorType": "Tween",
					"parameters": {
						"tags": "\"\"",
						"property": "offsetY",
						"end-value": "-500",
						"time": "1",
						"ease": "default",
						"destroy-on-complete": "no",
						"loop": "no",
						"ping-pong": "no",
						"repeat-count": "1"
					}
				},
				{
					"id": "tween-one-property",
					"objectClass": "lv1_q5",
					"sid": 212191234427141,
					"behaviorType": "Tween",
					"parameters": {
						"tags": "\"\"",
						"property": "offsetY",
						"end-value": "-500",
						"time": "1",
						"ease": "default",
						"destroy-on-complete": "no",
						"loop": "no",
						"ping-pong": "no",
						"repeat-count": "1"
					}
				},
				{
					"id": "tween-one-property",
					"objectClass": "lv1_q6",
					"sid": 383086831631745,
					"behaviorType": "Tween",
					"parameters": {
						"tags": "\"\"",
						"property": "offsetY",
						"end-value": "-500",
						"time": "1",
						"ease": "default",
						"destroy-on-complete": "no",
						"loop": "no",
						"ping-pong": "no",
						"repeat-count": "1"
					}
				},
				{
					"id": "subtract-from-instvar",
					"objectClass": "Mainplayer",
					"sid": 484629005080816,
					"parameters": {
						"instance-variable": "Heart",
						"value": "1"
					}
				},
				{
					"id": "subtract-from-instvar",
					"objectClass": "Mainplayer",
					"sid": 433819887931251,
					"parameters": {
						"instance-variable": "poin",
						"value": "5"
					}
				},
				{
					"id": "set-visible",
					"objectClass": "popupJawabanSalah",
					"sid": 219247138207803,
					"parameters": {
						"visibility": "visible"
					}
				},
				{
					"id": "set-position",
					"objectClass": "popupJawabanSalah",
					"sid": 122758571027695,
					"parameters": {
						"x": "pauseimg.X-735",
						"y": "LayoutHeight/2"
					}
				},
				{
					"id": "wait",
					"objectClass": "System",
					"sid": 201662295852985,
					"parameters": {
						"seconds": "2.0"
					}
				},
				{
					"id": "set-visible",
					"objectClass": "popupJawabanSalah",
					"sid": 218520218185055,
					"parameters": {
						"visibility": "invisible"
					}
				},
				{
					"id": "set-enabled",
					"objectClass": "Mainplayer",
					"sid": 943367724757968,
					"behaviorType": "Platform",
					"parameters": {
						"state": "enabled"
					}
				}
			],
			"sid": 204510898367884
		},
		{
			"eventType": "block",
			"conditions": [
				{
					"id": "on-tap-object",
					"objectClass": "Touch",
					"sid": 289691991291041,
					"parameters": {
						"object": "wrongans"
					}
				}
			],
			"actions": [
				{
					"id": "tween-one-property",
					"objectClass": "lv1_q1",
					"sid": 472216432736821,
					"behaviorType": "Tween",
					"parameters": {
						"tags": "\"\"",
						"property": "offsetY",
						"end-value": "-500",
						"time": "1",
						"ease": "default",
						"destroy-on-complete": "no",
						"loop": "no",
						"ping-pong": "no",
						"repeat-count": "1"
					}
				},
				{
					"id": "tween-one-property",
					"objectClass": "lv1_q2",
					"sid": 762863808609086,
					"behaviorType": "Tween",
					"parameters": {
						"tags": "\"\"",
						"property": "offsetY",
						"end-value": "-500",
						"time": "1",
						"ease": "default",
						"destroy-on-complete": "no",
						"loop": "no",
						"ping-pong": "no",
						"repeat-count": "1"
					}
				},
				{
					"id": "tween-one-property",
					"objectClass": "lv1_q3",
					"sid": 819451393887004,
					"behaviorType": "Tween",
					"parameters": {
						"tags": "\"\"",
						"property": "offsetY",
						"end-value": "-500",
						"time": "1",
						"ease": "default",
						"destroy-on-complete": "no",
						"loop": "no",
						"ping-pong": "no",
						"repeat-count": "1"
					}
				},
				{
					"id": "tween-one-property",
					"objectClass": "lv1_q4",
					"sid": 643903413349064,
					"behaviorType": "Tween",
					"parameters": {
						"tags": "\"\"",
						"property": "offsetY",
						"end-value": "-500",
						"time": "1",
						"ease": "default",
						"destroy-on-complete": "no",
						"loop": "no",
						"ping-pong": "no",
						"repeat-count": "1"
					}
				},
				{
					"id": "tween-one-property",
					"objectClass": "lv1_q5",
					"sid": 572329006493900,
					"behaviorType": "Tween",
					"parameters": {
						"tags": "\"\"",
						"property": "offsetY",
						"end-value": "-500",
						"time": "1",
						"ease": "default",
						"destroy-on-complete": "no",
						"loop": "no",
						"ping-pong": "no",
						"repeat-count": "1"
					}
				},
				{
					"id": "tween-one-property",
					"objectClass": "lv1_q6",
					"sid": 732831609456056,
					"behaviorType": "Tween",
					"parameters": {
						"tags": "\"\"",
						"property": "offsetY",
						"end-value": "-500",
						"time": "1",
						"ease": "default",
						"destroy-on-complete": "no",
						"loop": "no",
						"ping-pong": "no",
						"repeat-count": "1"
					}
				},
				{
					"id": "subtract-from-instvar",
					"objectClass": "Mainplayer",
					"sid": 527623547267223,
					"parameters": {
						"instance-variable": "Heart",
						"value": "1"
					}
				},
				{
					"id": "subtract-from-instvar",
					"objectClass": "Mainplayer",
					"sid": 851717015014044,
					"parameters": {
						"instance-variable": "poin",
						"value": "5"
					}
				},
				{
					"id": "set-visible",
					"objectClass": "popupJawabanSalah",
					"sid": 687161068681824,
					"parameters": {
						"visibility": "visible"
					}
				},
				{
					"id": "set-position",
					"objectClass": "popupJawabanSalah",
					"sid": 826895675785353,
					"parameters": {
						"x": "pauseimg.X-735",
						"y": "LayoutHeight/2"
					}
				},
				{
					"id": "wait",
					"objectClass": "System",
					"sid": 173225045736178,
					"parameters": {
						"seconds": "2.0"
					}
				},
				{
					"id": "set-visible",
					"objectClass": "popupJawabanSalah",
					"sid": 938062134000614,
					"parameters": {
						"visibility": "invisible"
					}
				},
				{
					"id": "set-enabled",
					"objectClass": "Mainplayer",
					"sid": 142899301726460,
					"behaviorType": "Platform",
					"parameters": {
						"state": "enabled"
					}
				}
			],
			"sid": 472976375757565
		},
		{
			"eventType": "block",
			"conditions": [
				{
					"id": "compare-x",
					"objectClass": "Mainplayer",
					"sid": 639953530230566,
					"parameters": {
						"comparison": 4,
						"x-co-ordinate": "844"
					}
				}
			],
			"actions": [
				{
					"id": "set-position-to-another-object",
					"objectClass": "lv1_obs_q1",
					"sid": 610586606160511,
					"parameters": {
						"object": "Mainplayer",
						"image-point-optional": "0"
					}
				}
			],
			"sid": 557656604881609
		},
		{
			"eventType": "block",
			"conditions": [
				{
					"id": "on-collision-with-another-object",
					"objectClass": "Mainplayer",
					"sid": 980055608279771,
					"parameters": {
						"object": "lv1_obs_q1"
					}
				}
			],
			"actions": [
				{
					"id": "wait",
					"objectClass": "System",
					"sid": 987165065054641,
					"parameters": {
						"seconds": "0.5"
					}
				},
				{
					"id": "destroy",
					"objectClass": "lv1_obs_q1",
					"sid": 454357841339794
				},
				{
					"id": "set-enabled",
					"objectClass": "Mainplayer",
					"sid": 287558621320900,
					"behaviorType": "Platform",
					"parameters": {
						"state": "disabled"
					}
				},
				{
					"id": "tween-one-property",
					"objectClass": "lv1_q1",
					"sid": 402384644033509,
					"behaviorType": "Tween",
					"parameters": {
						"tags": "\"\"",
						"property": "offsetY",
						"end-value": "LayoutHeight/2",
						"time": "1",
						"ease": "default",
						"destroy-on-complete": "no",
						"loop": "no",
						"ping-pong": "no",
						"repeat-count": "1"
					}
				},
				{
					"id": "play",
					"objectClass": "Audio",
					"sid": 165308564266550,
					"parameters": {
						"audio-file": "X2Download.app - 🎮👾 Retro Video Game Arcade 8 Bit [Sound Effects] Free Download Audio Background for Edits (128 kbps)-[AudioTrimmer.com] (1)",
						"loop": "not-looping",
						"volume": "75",
						"stereo-pan": "0",
						"tag-optional": "\"\""
					}
				}
			],
			"sid": 121502080786748
		},
		{
			"eventType": "block",
			"conditions": [
				{
					"id": "compare-x",
					"objectClass": "Mainplayer",
					"sid": 921647389022415,
					"parameters": {
						"comparison": 4,
						"x-co-ordinate": "1990"
					}
				}
			],
			"actions": [
				{
					"id": "set-position-to-another-object",
					"objectClass": "lv1_obs_q2",
					"sid": 722681023944697,
					"parameters": {
						"object": "Mainplayer",
						"image-point-optional": "0"
					}
				}
			],
			"sid": 493054716882040
		},
		{
			"eventType": "block",
			"conditions": [
				{
					"id": "on-collision-with-another-object",
					"objectClass": "Mainplayer",
					"sid": 672160991831795,
					"parameters": {
						"object": "lv1_obs_q2"
					}
				}
			],
			"actions": [
				{
					"id": "destroy",
					"objectClass": "lv1_obs_q2",
					"sid": 441498061321630
				},
				{
					"id": "wait",
					"objectClass": "System",
					"sid": 623626832673279,
					"parameters": {
						"seconds": "0.5"
					}
				},
				{
					"id": "set-enabled",
					"objectClass": "Mainplayer",
					"sid": 755300101596325,
					"behaviorType": "Platform",
					"parameters": {
						"state": "disabled"
					}
				},
				{
					"id": "tween-one-property",
					"objectClass": "lv1_q2",
					"sid": 415488375914696,
					"behaviorType": "Tween",
					"parameters": {
						"tags": "\"\"",
						"property": "offsetY",
						"end-value": "LayoutHeight/2",
						"time": "1",
						"ease": "default",
						"destroy-on-complete": "no",
						"loop": "no",
						"ping-pong": "no",
						"repeat-count": "1"
					}
				},
				{
					"id": "play",
					"objectClass": "Audio",
					"sid": 789194222666929,
					"parameters": {
						"audio-file": "X2Download.app - 🎮👾 Retro Video Game Arcade 8 Bit [Sound Effects] Free Download Audio Background for Edits (128 kbps)-[AudioTrimmer.com] (1)",
						"loop": "not-looping",
						"volume": "75",
						"stereo-pan": "0",
						"tag-optional": "\"\""
					}
				}
			],
			"sid": 913757592618174
		},
		{
			"eventType": "block",
			"conditions": [
				{
					"id": "compare-x",
					"objectClass": "Mainplayer",
					"sid": 141332776887563,
					"parameters": {
						"comparison": 4,
						"x-co-ordinate": "2800"
					}
				}
			],
			"actions": [
				{
					"id": "set-position-to-another-object",
					"objectClass": "lv1_obs_q3",
					"sid": 273002160389047,
					"parameters": {
						"object": "Mainplayer",
						"image-point-optional": "0"
					}
				}
			],
			"sid": 996381455912559
		},
		{
			"eventType": "block",
			"conditions": [
				{
					"id": "on-collision-with-another-object",
					"objectClass": "Mainplayer",
					"sid": 546839484315005,
					"parameters": {
						"object": "lv1_obs_q3"
					}
				}
			],
			"actions": [
				{
					"id": "destroy",
					"objectClass": "lv1_obs_q3",
					"sid": 174156855911042
				},
				{
					"id": "wait",
					"objectClass": "System",
					"sid": 149406314572315,
					"parameters": {
						"seconds": "0.5"
					}
				},
				{
					"id": "set-enabled",
					"objectClass": "Mainplayer",
					"sid": 174466045522447,
					"behaviorType": "Platform",
					"parameters": {
						"state": "disabled"
					}
				},
				{
					"id": "tween-one-property",
					"objectClass": "lv1_q3",
					"sid": 422897990105097,
					"behaviorType": "Tween",
					"parameters": {
						"tags": "\"\"",
						"property": "offsetY",
						"end-value": "LayoutHeight/2",
						"time": "1",
						"ease": "default",
						"destroy-on-complete": "no",
						"loop": "no",
						"ping-pong": "no",
						"repeat-count": "1"
					}
				},
				{
					"id": "play",
					"objectClass": "Audio",
					"sid": 827286626998536,
					"parameters": {
						"audio-file": "X2Download.app - 🎮👾 Retro Video Game Arcade 8 Bit [Sound Effects] Free Download Audio Background for Edits (128 kbps)-[AudioTrimmer.com] (1)",
						"loop": "not-looping",
						"volume": "75",
						"stereo-pan": "0",
						"tag-optional": "\"\""
					}
				}
			],
			"sid": 402528124322798
		},
		{
			"eventType": "block",
			"conditions": [
				{
					"id": "compare-x",
					"objectClass": "Mainplayer",
					"sid": 153677536411855,
					"parameters": {
						"comparison": 4,
						"x-co-ordinate": "4535"
					}
				}
			],
			"actions": [
				{
					"id": "set-position-to-another-object",
					"objectClass": "lv1_obs_q4",
					"sid": 833714688573899,
					"parameters": {
						"object": "Mainplayer",
						"image-point-optional": "0"
					}
				}
			],
			"sid": 886374225821903
		},
		{
			"eventType": "block",
			"conditions": [
				{
					"id": "on-collision-with-another-object",
					"objectClass": "Mainplayer",
					"sid": 161876129590024,
					"parameters": {
						"object": "lv1_obs_q4"
					}
				}
			],
			"actions": [
				{
					"id": "destroy",
					"objectClass": "lv1_obs_q4",
					"sid": 653474150344891
				},
				{
					"id": "wait",
					"objectClass": "System",
					"sid": 443901564424509,
					"parameters": {
						"seconds": "0.5"
					}
				},
				{
					"id": "set-enabled",
					"objectClass": "Mainplayer",
					"sid": 231637704734210,
					"behaviorType": "Platform",
					"parameters": {
						"state": "disabled"
					}
				},
				{
					"id": "tween-one-property",
					"objectClass": "lv1_q4",
					"sid": 609274081160567,
					"behaviorType": "Tween",
					"parameters": {
						"tags": "\"\"",
						"property": "offsetY",
						"end-value": "LayoutHeight/2",
						"time": "1",
						"ease": "default",
						"destroy-on-complete": "no",
						"loop": "no",
						"ping-pong": "no",
						"repeat-count": "1"
					}
				},
				{
					"id": "play",
					"objectClass": "Audio",
					"sid": 233124844568615,
					"parameters": {
						"audio-file": "X2Download.app - 🎮👾 Retro Video Game Arcade 8 Bit [Sound Effects] Free Download Audio Background for Edits (128 kbps)-[AudioTrimmer.com] (1)",
						"loop": "not-looping",
						"volume": "75",
						"stereo-pan": "0",
						"tag-optional": "\"\""
					}
				}
			],
			"sid": 786824527108980
		},
		{
			"eventType": "block",
			"conditions": [
				{
					"id": "compare-x",
					"objectClass": "Mainplayer",
					"sid": 508366025596596,
					"parameters": {
						"comparison": 4,
						"x-co-ordinate": "5500"
					}
				}
			],
			"actions": [
				{
					"id": "set-position-to-another-object",
					"objectClass": "lv1_obs_q5",
					"sid": 843273918445975,
					"parameters": {
						"object": "Mainplayer",
						"image-point-optional": "0"
					}
				}
			],
			"sid": 634471701170119
		},
		{
			"eventType": "block",
			"conditions": [
				{
					"id": "on-collision-with-another-object",
					"objectClass": "Mainplayer",
					"sid": 814056103753368,
					"parameters": {
						"object": "lv1_obs_q5"
					}
				}
			],
			"actions": [
				{
					"id": "destroy",
					"objectClass": "lv1_obs_q5",
					"sid": 977651163135356
				},
				{
					"id": "wait",
					"objectClass": "System",
					"sid": 421037997319424,
					"parameters": {
						"seconds": "0.5"
					}
				},
				{
					"id": "set-enabled",
					"objectClass": "Mainplayer",
					"sid": 460964108377477,
					"behaviorType": "Platform",
					"parameters": {
						"state": "disabled"
					}
				},
				{
					"id": "tween-one-property",
					"objectClass": "lv1_q5",
					"sid": 848605795809060,
					"behaviorType": "Tween",
					"parameters": {
						"tags": "\"\"",
						"property": "offsetY",
						"end-value": "LayoutHeight/2",
						"time": "1",
						"ease": "default",
						"destroy-on-complete": "no",
						"loop": "no",
						"ping-pong": "no",
						"repeat-count": "1"
					}
				},
				{
					"id": "play",
					"objectClass": "Audio",
					"sid": 143117766556327,
					"parameters": {
						"audio-file": "X2Download.app - 🎮👾 Retro Video Game Arcade 8 Bit [Sound Effects] Free Download Audio Background for Edits (128 kbps)-[AudioTrimmer.com] (1)",
						"loop": "not-looping",
						"volume": "75",
						"stereo-pan": "0",
						"tag-optional": "\"\""
					}
				}
			],
			"sid": 222823404477547
		},
		{
			"eventType": "block",
			"conditions": [
				{
					"id": "compare-x",
					"objectClass": "Mainplayer",
					"sid": 644963832406364,
					"parameters": {
						"comparison": 4,
						"x-co-ordinate": "6786"
					}
				}
			],
			"actions": [
				{
					"id": "set-position-to-another-object",
					"objectClass": "lv1_obs_q6",
					"sid": 566119551328740,
					"parameters": {
						"object": "Mainplayer",
						"image-point-optional": "0"
					}
				}
			],
			"sid": 617639932458499
		},
		{
			"eventType": "block",
			"conditions": [
				{
					"id": "on-collision-with-another-object",
					"objectClass": "Mainplayer",
					"sid": 215369747257312,
					"parameters": {
						"object": "lv1_obs_q6"
					}
				}
			],
			"actions": [
				{
					"id": "destroy",
					"objectClass": "lv1_obs_q6",
					"sid": 716094910375340
				},
				{
					"id": "wait",
					"objectClass": "System",
					"sid": 318958080204965,
					"parameters": {
						"seconds": "0.5"
					}
				},
				{
					"id": "set-enabled",
					"objectClass": "Mainplayer",
					"sid": 419377928659167,
					"behaviorType": "Platform",
					"parameters": {
						"state": "disabled"
					}
				},
				{
					"id": "tween-one-property",
					"objectClass": "lv1_q6",
					"sid": 720283144877674,
					"behaviorType": "Tween",
					"parameters": {
						"tags": "\"\"",
						"property": "offsetY",
						"end-value": "LayoutHeight/2",
						"time": "1",
						"ease": "default",
						"destroy-on-complete": "no",
						"loop": "no",
						"ping-pong": "no",
						"repeat-count": "1"
					}
				},
				{
					"id": "play",
					"objectClass": "Audio",
					"sid": 147151499093748,
					"parameters": {
						"audio-file": "X2Download.app - 🎮👾 Retro Video Game Arcade 8 Bit [Sound Effects] Free Download Audio Background for Edits (128 kbps)-[AudioTrimmer.com] (1)",
						"loop": "not-looping",
						"volume": "75",
						"stereo-pan": "0",
						"tag-optional": "\"\""
					}
				}
			],
			"sid": 852172505429167
		}
	],
	"sid": 285314590265717
}